{"podcast_id": "eb016f7614fd410c9c9efd899537691d", "treatment": "0", "episodes_analyzed": 2, "episodes_with_guests": 0, "total_guests": 0, "female_guests": 0, "urm_guests": 0, "female_percentage": 0, "urm_percentage": 0, "window_start": "2025-03-28", "window_end": "2025-06-26", "episode_details": [{"title": "Next Level w/ Kyle Walsh", "date": "2025-05-09T10:51:13", "guests": []}, {"title": "The Q2 Reset: 4 Questions to Refocus and Elevate Your Performance", "date": "2025-04-18T19:22:33", "guests": []}]}