{"podcast_id": "4ba8b7c66f254c0392c5e2397f29aed8", "treatment": "0", "episodes_analyzed": 3, "episodes_with_guests": 0, "total_guests": 0, "female_guests": 0, "urm_guests": 0, "female_percentage": 0, "urm_percentage": 0, "window_start": "2025-04-03", "window_end": "2025-07-02", "episode_details": [{"title": "What you need to know in case you get arrested", "date": "2025-06-10T21:24:28", "guests": []}, {"title": "What is Crime?", "date": "2025-05-20T11:25:06", "guests": []}, {"title": "Prison Food - It's Worse Than You Think", "date": "2025-04-07T07:28:00", "guests": []}]}