{"podcast_id": "38f41c5f268d4b779d138f2f432eb057", "treatment": "1", "episodes_analyzed": 28, "episodes_with_guests": 0, "total_guests": 0, "female_guests": 0, "urm_guests": 0, "female_percentage": 0, "urm_percentage": 0, "window_start": "2025-03-28", "window_end": "2025-06-26", "episode_details": [{"title": "The BIGGEST THING a PERSON NEEDS in their LIFE is PEACE of MIND #peace #peaceofmind #tranquility #content", "date": "2025-06-25T12:36:43", "guests": []}, {"title": "SOME UNPLEASANT TRUTHS about MARRIAGE #cardrive #marriage #mrcv #truth #bittertruth #viralvideo#fyp", "date": "2025-06-24T15:51:29", "guests": []}, {"title": "THIRTEEN RULES to IMPROVE YOURSELF #cardrive #thirteen #rules#improve#improveyourself#viralvideo#fyp", "date": "2025-06-24T15:44:48", "guests": []}, {"title": "WORK with INTEGRITY and DON'T CHEAT PEOPLE #dailytalks #mrcv #integrity#cheating#cheat#honesty#work", "date": "2025-06-24T15:35:14", "guests": []}, {"title": "SOME VITAL RULES for FINANCIAL SUCCESS #cardrive #rules #finance#financial #success#vital#viralvideo", "date": "2025-06-24T15:31:46", "guests": []}, {"title": "SOME PSYCHOLOGICAL FACTS No-One TALKS ABOUT #cardrive #psychology #psychological #facts #mrcv #fyp", "date": "2025-06-24T15:24:52", "guests": []}, {"title": "TWELVE LIFE LESSONS #cardrive #life #lesson #lessons #lifelessons #mrcv #viralvideo #explorepage", "date": "2025-06-24T15:17:50", "guests": []}, {"title": "LIFE INSIGHTS #life #cardrive #insights #insight #mrcv #listen #reality #explorepage", "date": "2025-06-24T15:02:53", "guests": []}, {"title": "NINE THOUGHTS that WILL CHANGE YOUR LIFE #cardrive #thoughts#mrcv#mindset#viralvideo#explorepage#fyp", "date": "2025-06-24T14:53:25", "guests": []}, {"title": "SOME GOLDEN RULES in a RELATIONSHIP #cardrive #golden#rules#relationship#life#reality#viralvideo#fyp", "date": "2025-06-24T14:42:18", "guests": []}, {"title": "LIFE LESSONS You MIGHT OFTEN LEARN the HARD WAY #cardrive #mrcv #life#reality#viralvideo#listen#fyp", "date": "2025-06-24T14:31:08", "guests": []}, {"title": "REASONS why SOME MEN are POOR in their 40s #listen #poor #takenote #reality #life", "date": "2025-06-09T21:24:50", "guests": []}, {"title": "UNCOMFORTABLE TRUTHS MEN NEED to HEAR #uncomfortable #truths #men #need", "date": "2025-06-09T17:48:21", "guests": []}, {"title": "These RULES will make YOU a MACHO MAN #rules #respect #man #listen", "date": "2025-06-09T17:45:31", "guests": []}, {"title": "Happy EID and LEARN to be PATIENT #eid #patient #Muslim #Islam #patience #patient", "date": "2025-06-09T17:41:32", "guests": []}, {"title": "These REMINDERS will MAKE YOU STRONGER #strength #stronger #wiser #wisdom", "date": "2025-06-03T15:55:13", "guests": []}, {"title": "These are the THINGS You SHOULD KNOW from 18 to 55 #CarDrive", "date": "2025-06-02T14:17:10", "guests": []}, {"title": "The BATTLE of the MIND: Can you WIN It?? #DailyTalks", "date": "2025-06-02T14:14:57", "guests": []}, {"title": "LEARN to LOOK AFTER YOURSELF and Take YOURSELF out #DailyTalks", "date": "2025-06-02T14:11:29", "guests": []}, {"title": "PROTECT your ENERGY and REMEMBER you're an ASSET", "date": "2025-05-30T13:09:33", "guests": []}, {"title": "Some MIND BLOWING LIFE HACKS for YOU. It MIGHT HELP, Soo LISTEN WELL!", "date": "2025-05-29T12:54:04", "guests": []}, {"title": "By the AGE of 30, MASTER these SKILLS if you WANT to be 10 YEARS AHEAD #cardrive #mrcv #listen #fyp", "date": "2025-05-17T09:16:51", "guests": []}, {"title": "HARD LIFE LESSONS EVERYONE SHOULD LEARN #cardrive #mrcv #cvtalks #lifelessons #life #viralvideo#fyp", "date": "2025-05-05T16:07:32", "guests": []}, {"title": "These 20 Life Lessons WILL take you to ANOTHER LEVEL #mrcv #lifelesson #learning #anotherlevel", "date": "2025-04-23T14:40:54", "guests": []}, {"title": "21 SKILLS that WILL PAY YOU FOREVER (Upgraded and Updated) #mrcv#cvtalks#viralvideo#explorepage#fyp", "date": "2025-04-20T09:25:24", "guests": []}, {"title": "MEN, FOCUS on THIS and You'll SET YOURSELF 10 YEARS AHEAD within 6 MONTHS", "date": "2025-04-03T09:00:00", "guests": []}, {"title": "12 THINGS You LEARN as You GET OLDER #learning #learn #mrcv #older #life #reality", "date": "2025-04-02T09:00:00", "guests": []}, {"title": "What are SOME THINGS You REALISED when you got MATURE? #mature #maturity #mrcv #cardrive", "date": "2025-04-01T16:18:06", "guests": []}]}