{
  "guest_name": "Pump Action",
  "searched_at": "2025-07-10T16:47:53.768767",
  "search_results": [
    {
      "title": "Sawed-Off & Turned-Up: an Interview with Pump Action",
      "snippet": "Pump Action is a rock band from Miami, Florida currently living and working in Nashville, Tennessee. Their most recent singles are \u201cEuphoria\u201d & \u201cLeave My Girl ...",
      "link": "https://wp0.vanderbilt.edu/nashvillereview/archives/19540"
    },
    {
      "title": "The Duality of Euphoria: Pleasure and Pain in Music",
      "snippet": "Pump Action's \u201cEuphoria\u201d narrates a seductive tale of addiction, using funk's irony to explore themes of mental decline, isolation, and existential crisis.",
      "link": "https://bsideguys.com/2024/11/09/the-duality-of-euphoria-pleasure-and-pain-in-music/"
    },
    {
      "title": "Pump Action",
      "snippet": "& with this pump action, an object bullets through the wind: a boy ... Author of \"Nature knows a little about Slave Trade\" selected by Tate.",
      "link": "https://www.pangyrus.com/poetry/pump-action/"
    }
  ],
  "enhanced_gender": null,
  "enhanced_race": null,
  "gender_confidence": 0.0,
  "race_confidence": 0.0,
  "additional_context": {}
}