{
  "guest_name": "Jasper Troy",
  "searched_at": "2025-07-10T17:32:14.293446",
  "search_results": [
    {
      "title": "Author: Jasper Troy",
      "snippet": "Author, Community, Forum. Jasper Troy PM \u00b7 My Stories . Bio Fav: Authors. Biography. Joined Oct 9, 2009. When I created my profile I had the full intention of ...",
      "link": "https://m.fanfiction.net/u/2109255/?a=b"
    },
    {
      "title": "Jasper Troy - Pro Wrestlers Database",
      "snippet": "On this page, you find the full wrestling profile of Jasper Troy, with his Career History, real name, age, height and weight, the Promotions he worked for.",
      "link": "https://www.thesmackdownhotel.com/wrestlers/jasper-troy"
    },
    {
      "title": "Jasper Troy - Facts @ Wrestlingdata.com",
      "snippet": "Jasper Troy. General Information. Real Name, Antione Frazier. Weight and Height, 340 lbs ...",
      "link": "https://www.wrestlingdata.com/index.php?befehl=bios&wrestler=40729"
    }
  ],
  "enhanced_gender": "Male",
  "enhanced_race": null,
  "gender_confidence": 0.8,
  "race_confidence": 0.0,
  "additional_context": {}
}