{
  "guest_name": "Nike X",
  "searched_at": "2025-07-10T15:58:09.645389",
  "search_results": [
    {
      "title": "Nike-X",
      "snippet": "Nike-X was an anti-ballistic missile (ABM) system designed in the 1960s by the United States Army to protect major cities in the United States",
      "link": "https://en.wikipedia.org/wiki/Nike-X"
    },
    {
      "title": "All Stories",
      "snippet": "Nike x LEGO\u00ae Collection \u00b7 SNKRS Launch Calendar \u00b7 Shop All Sale \u00b7 Shop New \u00b7 Men \u00b7 Women \u00b7 Kids \u00b7 Shop All. Trending. 24.7 Collection \u00b7 Nike Form Collection.",
      "link": "https://www.nike.com/stories/all"
    },
    {
      "title": "Nike x Gurls Talk",
      "snippet": "Nike partnered with Gurls Talk and we elevated their platform by launching a podcast with over 60 episodes, created Instagram content, a Nike x Gurls Talk ...",
      "link": "http://www.november-romeo.com/nike-women-1"
    }
  ],
  "enhanced_gender": null,
  "enhanced_race": null,
  "gender_confidence": 0.0,
  "race_confidence": 0.0,
  "additional_context": {}
}