{
  "guest_name": "Fraxiom",
  "searched_at": "2025-07-10T17:32:18.136312",
  "search_results": [
    {
      "title": "The CHEEKY Issue: Fraxiom",
      "snippet": "24-year-old Fraxiom quickly rose to fame with the quarantine hyperpop boom. Alongside fellow producer Gupi, they form half of Food House and have been a staple ...",
      "link": "https://www.emmiemusic.com/interviews/the-cheeky-issue-fraxiom"
    },
    {
      "title": "Fraxiom's Year of Rest and Relaxation",
      "snippet": "If you woke up and you were Drake, what would you do? She/her in bio. Shut off phone. Yes! That's it? Just go to bed and wake up as Fraxiom ...",
      "link": "https://www.ringtonemag.com/articles/fraxioms-year-of-rest-and-relaxation"
    },
    {
      "title": "Fraxiom Keeps It Fresh - These Days",
      "snippet": "We caught up with Fraxiom to talk about moving to Chicago, their production methods, and their plans for this year.",
      "link": "https://thesedaysmag.com/articles/fraxiom-keeps-it-fresh"
    }
  ],
  "enhanced_gender": null,
  "enhanced_race": null,
  "gender_confidence": 0.0,
  "race_confidence": 0.0,
  "additional_context": {}
}