{
  "guest_name": "Captain Three Leg",
  "searched_at": "2025-07-10T17:11:58.258683",
  "search_results": [
    {
      "title": "Captain 3 Leg - discography, line-up, biography, interviews ...",
      "snippet": "Also known as Captain Three Leg ; Style Grindcore ; Status Active ; Formed In 1995 ; CountryUSA.",
      "link": "https://www.spirit-of-metal.com/en/band/Captain_3_Leg"
    },
    {
      "title": "Captain Three Leg discography",
      "snippet": "Captain Three Leg discography and songs: Music profile for Captain Three Leg, formed 1995. Genres: Grindcore, Noisecore, Noisegrind.",
      "link": "https://rateyourmusic.com/artist/captain-three-leg"
    },
    {
      "title": "Captain Three Leg songs",
      "snippet": "A grind/noise band from Philiadelphia, Pennsylvania. Formed in 1995.... Read More About Captain Three Leg Biography... Send Captain Three Leg ringtones to your ...",
      "link": "https://artistwiki.com/captain-three-leg"
    }
  ],
  "enhanced_gender": null,
  "enhanced_race": null,
  "gender_confidence": 0.0,
  "race_confidence": 0.0,
  "additional_context": {}
}