{
  "guest_name": "Travis Hudson",
  "searched_at": "2025-07-10T15:28:42.519159",
  "search_results": [
    {
      "title": "Travis Hudson: books, biography, latest update",
      "snippet": "Follow Travis Hudson and explore their bibliography from Amazon's Travis Hudson Author Page.",
      "link": "https://www.amazon.com/stores/author/B001KCLWU4"
    },
    {
      "title": "Travis Hudson: books, biography, latest update",
      "snippet": "Follow Travis Hudson and explore their bibliography from Amazon's Travis Hudson Author Page.",
      "link": "https://www.amazon.com/Travis-Hudson/e/B0028AV2P2?ref=dbs_a_def_rwt_hsch_vu00_taft_p1_i0"
    },
    {
      "title": "Travis Hudson, MPH | COPH Faculty Profile - USF Health",
      "snippet": "Travis Hudson, MPH, Instructor I, Contact Info, Education, Specialization, University of South Florida College of Public Health.",
      "link": "https://health.usf.edu/publichealth/overviewcoph/faculty/travishudson"
    }
  ],
  "enhanced_gender": null,
  "enhanced_race": null,
  "gender_confidence": 0.0,
  "race_confidence": 0.0,
  "additional_context": {}
}