{
  "guest_name": "Ogden, Winderick and Stack",
  "searched_at": "2025-07-10T16:49:08.725920",
  "search_results": [
    {
      "title": "BEVA pod Podcast",
      "snippet": "... Ogden, Winderick and Stack's article: Computed tomography of the equine caudal spine and pelvis. Pathological findings in 56 clinical cases (2018\u20132023). 12 ...",
      "link": "https://podcasts.apple.com/br/podcast/beva-pod/id1483234049?l=en-GB"
    },
    {
      "title": "BEVA pod - Podcasts-Online.org",
      "snippet": "... Ogden, Winderick and Stack's article: Computed tomography of the equine caudal spine and pelvis. Pathological findings in 56 clinical cases (2018\u20132023). Fri ...",
      "link": "https://www.podcasts-online.org/pt/beva-pod-1483234049"
    },
    {
      "title": "BEVApod Life: Being Brave and Trying New Things with Equine ...",
      "snippet": "Ogden, Winderick and Stack's article: Computed tomography of the equine caudal spine and pelvis. Pathological findings in 56 clinical cases (2018\u20132023). 12 ...",
      "link": "https://uk-podcasts.co.uk/podcast/beva-pod/bevapod-life-being-brave-and-trying-new-things-wit"
    }
  ],
  "enhanced_gender": null,
  "enhanced_race": null,
  "gender_confidence": 0.0,
  "race_confidence": 0.0,
  "additional_context": {}
}