{
  "guest_name": "Mat Wilson",
  "searched_at": "2025-07-10T15:29:49.738824",
  "search_results": [
    {
      "title": "Mat Wilson - CEO - Immortal Media",
      "snippet": "Mat Wilson. Founder of immortal media & The Entrepreneurs Marketing Conference Digital marketing expert, public speaker and entrepreneur. Immortal Media St.",
      "link": "https://uk.linkedin.com/in/mat-wilson-5184b913a"
    },
    {
      "title": "Mat Wilson: books, biography, latest update",
      "snippet": "Follow Mat Wilson and explore their bibliography from Amazon's Mat Wilson Author Page.",
      "link": "https://www.amazon.com/Mat-Wilson/e/B00BK7BAGU"
    },
    {
      "title": "Mat Wilson Motivation",
      "snippet": "Welcome to the Mat Wilson Motivation Channel! Mat is a motivational speaker, CEO of Einstein Marketer, a digital marketing agency operating out of London, UK.",
      "link": "https://www.youtube.com/c/matwilsonmotivation"
    }
  ],
  "enhanced_gender": null,
  "enhanced_race": null,
  "gender_confidence": 0.0,
  "race_confidence": 0.0,
  "additional_context": {}
}