{
  "guest_name": "Mama Vicki",
  "searched_at": "2025-07-10T16:30:26.312241",
  "search_results": [
    {
      "title": "\u2600\ufe0f ~ Vicki Rivard, author of Brave New Mama https://www. ...",
      "snippet": "\u2600\ufe0f ~ Vicki Rivard, author of Brave New Mama https://www.amazon.com/brave-new-mama-Vicki- Rivard/dp/0995294801 \u00b7 Looking for a wonderful book to read this summer?",
      "link": "https://m.facebook.com/birthbreathanddeath/posts/%EF%B8%8F-vicki-rivard-author-of-brave-new-mama-httpswwwamazoncombrave-new-mama-vicki-ri/853695876766278/"
    },
    {
      "title": "brave new mama - Rivard, Vicki: Books",
      "snippet": "She captures in few words what the birthing and new mothering experience is like for many of us; an indescribable breaking open of the heart, a falling in love ...",
      "link": "https://www.amazon.com/brave-new-mama-Vicki-Rivard/dp/0995294801"
    },
    {
      "title": "Vicki Rivard, author of Brave New Mama",
      "snippet": "Vicki Rivard, author of Brave New Mama https://www.amazon.com/brave-new-mama-Vicki-Rivard/dp/0995294801.",
      "link": "https://www.facebook.com/photo.php?fbid=853695756766290&id=100063776192618&set=a.490862353049634&locale=lv_LV"
    }
  ],
  "enhanced_gender": "Female",
  "enhanced_race": null,
  "gender_confidence": 0.8,
  "race_confidence": 0.0,
  "additional_context": {}
}