{
  "guest_name": "interdimensional beings",
  "searched_at": "2025-07-10T15:02:07.318885",
  "search_results": [
    {
      "title": "Interdimensional Universe: The New Science of UFOs, ...",
      "snippet": "Imbrogno's investigation into the powerful and mysterious interdimensional beings known as djinn or genies.",
      "link": "https://www.amazon.com/Interdimensional-Universe-Paranormal-Phenomena-Otherdimensional/dp/0738713473"
    },
    {
      "title": "Dr. Steven Greer on Interdimensional Beings (Part 17)",
      "snippet": "There are phenomenon that are emerging from other dimensions that occasionally interface with this dimension of 3D space time.",
      "link": "https://www.youtube.com/watch?v=8RaOc5y8cdA"
    },
    {
      "title": "Daniel Nemes's (REAL) interdimensional photos # 1-80",
      "snippet": "Scientist creates a chamber that captures interdimensional beings. His name is Daniel Nemes, he is Spanish but has been living in Colombia for several years ...",
      "link": "https://www.facebook.com/media/set/?set=a.1036253833238665&s=15"
    }
  ],
  "enhanced_gender": "Male",
  "enhanced_race": null,
  "gender_confidence": 0.8,
  "race_confidence": 0.0,
  "additional_context": {}
}