{
  "guest_name": "the angel",
  "searched_at": "2025-07-10T17:24:13.144479",
  "search_results": [
    {
      "title": "The Angel Professor | Chilling Silence",
      "snippet": "The Angel Professor. Light shines brightest in the darkest place. Latest \u00b7 First \u00b7 Archive \u00b7 Scroll View \u00b7 Blog \u00b7 Patreon \u00b7 Search \u00b7 Characters \u00b7 Image Gallery ...",
      "link": "https://theangelprof.thecomicseries.com/"
    },
    {
      "title": "Gone is the angel: The biography of one of Canada's ...",
      "snippet": "Gone is the angel: The biography of one of Canada's unsung heroes, Wing Commander L.V. Chadburn, DSO & BAR, DFC ; ISBN-10, 0968187501 ; ISBN-13, 978-0968187500 ...",
      "link": "https://www.amazon.ca/Gone-angel-biography-Commander-Chadburn/dp/0968187501"
    },
    {
      "title": "The Angel - Hans Christian Andersen",
      "snippet": "The angel took up the rose-bush; then he kissed the child, and the little one half opened his eyes. The angel gathered also some beautiful flowers, as well ...",
      "link": "http://hca.gilead.org.il/angel.html"
    }
  ],
  "enhanced_gender": "Male",
  "enhanced_race": null,
  "gender_confidence": 0.8,
  "race_confidence": 0.0,
  "additional_context": {}
}