{
  "guest_name": "Uwos Lab",
  "searched_at": "2025-07-10T17:36:24.722175",
  "search_results": [
    {
      "title": "Uwos Lab",
      "snippet": "Uwos Lab ; I Spun CHEAP COINS like BEYBLADES and Here's What Happened. 15K views ; I turned ENERGY DRINKS into ROCKET FUEL. 14K views ; I Built a Toilet Paper Slot ...",
      "link": "https://www.youtube.com/@UwosLab"
    }
  ],
  "enhanced_gender": null,
  "enhanced_race": null,
  "gender_confidence": 0.0,
  "race_confidence": 0.0,
  "additional_context": {}
}