{
  "guest_name": "Carr Brothers",
  "searched_at": "2025-07-10T15:07:45.957494",
  "search_results": [
    {
      "title": "The Carr Brothers Talk #Beyonce: There is a first time for ...",
      "snippet": "The Carr Brothers Talk #Beyonce: There is a first time for everything ... A few weeks ago, I had the opportunity to do something I'd never done ...",
      "link": "https://thecarrwindow.com/2020/09/18/the-carr-brothers-talk-beyonce-there-is-a-first-time-for-everything/"
    },
    {
      "title": "Photographs of Dr Henry Carr are rare",
      "snippet": "Dr. Carr's grandson Warren Carr, who has become an invaluable resource for the book, told me about the Carr brothers' inclusion in the \u201cFirst ...",
      "link": "https://www.facebook.com/groups/595722337727182/posts/1647625052536900/"
    },
    {
      "title": "Caleb Carr",
      "snippet": "Caleb Carr (August 2, 1955 \u2013 May 23, 2024) was an American military historian and author. ... Carr brothers bonded, a group that Caleb would label \"the dark Brady ...",
      "link": "https://en.wikipedia.org/wiki/Caleb_Carr"
    }
  ],
  "enhanced_gender": null,
  "enhanced_race": null,
  "gender_confidence": 0.0,
  "race_confidence": 0.0,
  "additional_context": {}
}