{
  "guest_name": "Jacob Paris",
  "searched_at": "2025-07-10T14:55:38.292178",
  "search_results": [
    {
      "title": "Jacob Paris - intaneous",
      "snippet": "Jacob Paris - intaneous RMIT University About A software developer and designer working extensively in game engines and other software.",
      "link": "https://au.linkedin.com/in/jacob-paris-719ab43b"
    },
    {
      "title": "P. L. Jacob - Paris Ridicule Et Burlesque Au Dix-Septieme ...",
      "snippet": "P. L. Jacob - Paris Ridicule Et Burlesque Au Dix-Septieme Siecle - 1859 ; Est. delivery. Thu, Jun 26 - Wed, Jul 16. From Aliano, Italy ; Returns. Accepted within ...",
      "link": "https://www.ebay.com/itm/387388043715"
    },
    {
      "title": "The Fall of France Seen by Max Jacob",
      "snippet": "12 B\u00e9atrice Mousli, Max Jacob (Paris: Flammarion, 2005), 423. 13 To Manoll, 2 August, 1940: Manoll 1985, 63\u20134. 14 To Manoll, 21 August, 1940 ...",
      "link": "https://muse.jhu.edu/pub/1/article/942318/pdf"
    }
  ],
  "enhanced_gender": null,
  "enhanced_race": null,
  "gender_confidence": 0.0,
  "race_confidence": 0.0,
  "additional_context": {}
}