{
  "guest_name": "Carlos Prates",
  "searched_at": "2025-07-10T15:36:01.083818",
  "search_results": [
    {
      "title": "Carlos Prates",
      "snippet": "As of November 12, 2024, he is #13 in the UFC welterweight rankings. Carlos Prates. Born, Carlos Augusto Monteiro Prates",
      "link": "https://en.wikipedia.org/wiki/Carlos_Prates"
    },
    {
      "title": "Carlos Prates Biography",
      "snippet": "CarlosPrates ; Birthdate. 8/17/1993 (31) ; Team. Fighting Nerds ; CountryBrazil ; WT ClassWelterweight ; HT/WT6' 1\", 171 lbs.",
      "link": "https://www.espn.com/mma/fighter/bio/_/id/4294832/carlos-prates"
    },
    {
      "title": "Luiz Carlos Prates",
      "snippet": "Luiz Carlos Prates (born January 26, 1943, in Santiago do Brasil) is a Brazilian journalist, psychologist, and radio sport announcer.",
      "link": "https://en.wikipedia.org/wiki/Luiz_Carlos_Prates"
    }
  ],
  "enhanced_gender": "Male",
  "enhanced_race": null,
  "gender_confidence": 0.8,
  "race_confidence": 0.0,
  "additional_context": {}
}