{
  "guest_name": "Molly Wryn",
  "searched_at": "2025-07-10T16:17:37.520606",
  "search_results": [
    {
      "title": "Molly Wryn",
      "snippet": "Molly Wryn is known for Dune (1984), Banned, Exploited & Blacklisted: The Underground Work of Controversial Filmmaker Shane Ryan (2020) and Warning!!!",
      "link": "https://www.imdb.com/name/nm0943047/"
    },
    {
      "title": "Molly Wryn - Biography",
      "snippet": "Molly Wryn is known for Dune (1984), Banned, Exploited & Blacklisted: The Underground Work of Controversial Filmmaker Shane Ryan (2020) and Warning!!!",
      "link": "https://www.imdb.com/name/nm0943047/bio/"
    },
    {
      "title": "Molly Wryn - Writer, Producer, Actor - Free Lance",
      "snippet": "Writer, Producer, Actor at Free Lance \u00b7 Experience: Free Lance \u00b7 Location: Portland. View Molly Wryn's profile on LinkedIn, a professional community of 1 ...",
      "link": "https://www.linkedin.com/in/molly-wryn-639a5b103"
    }
  ],
  "enhanced_gender": null,
  "enhanced_race": null,
  "gender_confidence": 0.0,
  "race_confidence": 0.0,
  "additional_context": {}
}